DBManager/__init__.py
DBManager/dbmanager.py
DBManager-0.1.3.dist-info/METADATA
DBManager-0.1.3.dist-info/RECORD
DBManager-0.1.3.dist-info/WHEEL
DBManager-0.1.3.dist-info/top_level.txt
