Metadata-Version: 2.1
Name: DBManager
Version: 0.1.3
Summary: Make Database Managing easier!
Home-page: https://github.com/LeCuay/DBManager.py
Author: LeCuay
License: UNKNOWN
Platform: UNKNOWN
Classifier: Development Status :: 3 - Alpha
Classifier: Programming Language :: Python :: 3.6
Classifier: License :: OSI Approved :: MIT License
Classifier: Operating System :: OS Independent
Classifier: Topic :: Software Development :: Libraries
Classifier: Topic :: Software Development :: Libraries :: Python Modules
Classifier: Topic :: Utilities
